HISTORY.rst
LICENSE.txt
MANIFEST.in
README.md
setup.py
caffeinated_hound.egg-info/PKG-INFO
caffeinated_hound.egg-info/SOURCES.txt
caffeinated_hound.egg-info/dependency_links.txt
caffeinated_hound.egg-info/entry_points.txt
caffeinated_hound.egg-info/not-zip-safe
caffeinated_hound.egg-info/requires.txt
caffeinated_hound.egg-info/top_level.txt
hound/__init__.py
hound/handlers.py
hound/scripts.py