Metadata-Version: 1.0
Name: caffeinated-hound
Version: 0.1.0
Summary: CoffeeScript watcher and compiler.
Home-page: https://github.com/marconi/caffeinated-hound
Author: Marconi Moreto
Author-email: caketoad@gmail.com
License: Copyright (c) 2012 Marconi Moreto.
